{
  "reservas": [
    {
      "id": "RES1739522252841",
      "fecha": "14/02/2025, 09:37",
      "mes": "febrero",
      "cliente": {
        "id": "1736494591754",
        "nombre": "Yuki",
        "apellidos": "Tanaka",
        "edad": 31,
        "nacionalidad": "Japonesa",
        "hijos": 0
      },
      "habitacion": {
        "tipo": "Habitación cuádruple",
        "precio": 300
      },
      "regimen": {
        "tipo": "media pension",
        "precio": 45
      },
      "servicios": [
        {
          "nombre": "Excursiones",
          "precio": 100
        }
      ],
      "precioTotal": 545
    },
    {
      "id": "RES1739522312469",
      "fecha": "14/02/2025, 09:38",
      "mes": "febrero",
      "cliente": {
        "id": "1736494591753",
        "nombre": "Hans",
        "apellidos": "Weber",
        "edad": 38,
        "nacionalidad": "Alemana",
        "hijos": 2
      },
      "habitacion": {
        "tipo": "Habitación estándar",
        "precio": 150
      },
      "regimen": {
        "tipo": "solo desayuno",
        "precio": 25
      },
      "servicios": [
        {
          "nombre": "Excursiones",
          "precio": 100
        },
        {
          "nombre": "Parking",
          "precio": 25
        }
      ],
      "precioTotal": 450
    },
    {
      "id": "RES1739522350401",
      "fecha": "14/02/2025, 09:39",
      "mes": "febrero",
      "cliente": {
        "id": "1736494591754",
        "nombre": "Yuki",
        "apellidos": "Tanaka",
        "edad": 31,
        "nacionalidad": "Japonesa",
        "hijos": 0
      },
      "habitacion": {
        "tipo": "Habitación económica",
        "precio": 90
      },
      "regimen": {
        "tipo": "solo desayuno",
        "precio": 25
      },
      "servicios": [
        {
          "nombre": "Parking",
          "precio": 25
        }
      ],
      "precioTotal": 255
    },
    {
      "id": "RES1739522372380",
      "fecha": "14/02/2025, 09:39",
      "mes": "febrero",
      "cliente": {
        "id": "1732870380351",
        "nombre": "Sandra",
        "apellidos": "Gonzalez",
        "edad": 30,
        "nacionalidad": "Española",
        "hijos": 2
      },
      "habitacion": {
        "tipo": "Habitación de lujo",
        "precio": 800
      },
      "regimen": {
        "tipo": "solo desayuno",
        "precio": 25
      },
      "servicios": [
        {
          "nombre": "Parking",
          "precio": 25
        }
      ],
      "precioTotal": 900
    },
    {
      "id": "RES1739523427338",
      "fecha": "14/02/2025, 09:57",
      "mes": "febrero",
      "cliente": {},
      "habitacion": {
        "tipo": "Suite presidencial",
        "precio": 1000
      },
      "regimen": {
        "tipo": "solo desayuno",
        "precio": 25
      },
      "servicios": [],
      "precioTotal": 1300
    },
    {
      "id": "RES1739523483601",
      "fecha": "14/02/2025, 09:58",
      "mes": "febrero",
      "cliente": {},
      "habitacion": {
        "tipo": "Suite presidencial",
        "precio": 1000
      },
      "regimen": {
        "tipo": "solo desayuno",
        "precio": 25
      },
      "servicios": [],
      "precioTotal": 1300
    },
    {
      "id": "RES1739523551263",
      "fecha": "14/02/2025, 09:59",
      "mes": "febrero",
      "cliente": {},
      "habitacion": {
        "tipo": "Habitación estándar",
        "precio": 150
      },
      "regimen": {
        "tipo": "solo desayuno",
        "precio": 25
      },
      "servicios": [],
      "precioTotal": 650
    }
  ]
}